<?xml version="1.0" encoding="utf-8"?>
<publishData>
  <publishProfile publishUrl="\\hqolymgis21t\Websites\GeoPortal" deleteExistingFiles="True" ftpAnonymousLogin="False" ftpPassiveMode="True" msdeploySite="" msdeploySiteID="" msdeployRemoteSitePhysicalPath="" msdeployAllowUntrustedCertificate="False" msdeploySkipExtraFilesOnServer="True" msdeployMarkAsApp="False" profileName="GeoPortal (21T)" publishMethod="FileSystem" replaceMatchingFiles="False" userName="" savePWD="False" userPWD="" SelectedForPublish="True">
    <file relUrl="bin/GeoPortal.pdb" publishTime="01/24/2012 15:41:52" />
    <file relUrl="images/ajax-loader.gif" publishTime="03/21/2011 13:56:45" />
    <file relUrl="scripts/htmlPopupExtensions.js" publishTime="12/21/2011 12:27:32" />
    <file relUrl="style/layerList.css" publishTime="11/08/2011 10:50:58" />
    <file relUrl="style/identify.css" publishTime="08/01/2011 13:29:55" />
    <file relUrl="help/zoom_controls.html" publishTime="10/12/2011 14:07:10" />
    <file relUrl="style/layerSorter.css" publishTime="11/08/2011 17:07:17" />
    <file relUrl="bin/GeoPortal.dll" publishTime="01/24/2012 15:41:52" />
    <file relUrl="bin/Google.KML.dll" publishTime="07/13/2011 14:14:49" />
    <file relUrl="web.config" publishTime="01/24/2012 15:42:02" />
    <file relUrl="scripts/toc.js" publishTime="11/07/2011 14:22:28" />
    <file relUrl="FunctionalClassLegend.html" publishTime="11/07/2011 14:22:28" />
    <file relUrl="images/WsdotBasemapThumbnail.jpg" publishTime="05/25/2011 12:49:05" />
    <file relUrl="style/index.css" publishTime="01/25/2012 12:50:43" />
    <file relUrl="images/NorthArrow.png" publishTime="03/22/2011 16:21:43" />
    <file relUrl="ReadMe.html" publishTime="11/07/2011 14:32:43" />
    <file relUrl="images/FCBasemapThumbnail.png" publishTime="05/25/2011 12:52:57" />
    <file relUrl="help/measure.html" publishTime="07/06/2011 13:42:43" />
    <file relUrl="index.html" publishTime="01/23/2012 16:24:50" />
    <file relUrl="images/greenlogo.png" publishTime="02/23/2011 08:50:45" />
    <file relUrl="images/layerList/contextMenu.png" publishTime="11/02/2011 14:58:23" />
    <file relUrl="scripts/jquery.pnotify.min.js" publishTime="07/15/2011 13:27:08" />
    <file relUrl="GraphicExport.ashx" publishTime="07/05/2011 16:57:31" />
    <file relUrl="scripts/extentSelect.js" publishTime="10/12/2011 14:07:10" />
    <file relUrl="images/navigation/FeedbackIcon.png" publishTime="07/01/2011 10:35:45" />
    <file relUrl="scripts/json2.js" publishTime="01/26/2011 10:03:51" />
    <file relUrl="style/jquery.pnotify.default.icons.css" publishTime="03/16/2011 09:47:53" />
    <file relUrl="style/jquery.pnotify.default.css" publishTime="03/16/2011 09:47:53" />
    <file relUrl="scripts/layerSorter.js" publishTime="11/08/2011 16:40:31" />
    <file relUrl="scripts/cameraGraphicsLayer.js" publishTime="08/15/2011 12:47:54" />
    <file relUrl="style/locationInfo.css" publishTime="07/12/2011 16:58:38" />
    <file relUrl="images/layerList/treePlus10.gif" publishTime="11/02/2011 14:58:23" />
    <file relUrl="proxy.ashx" publishTime="04/22/2011 12:22:41" />
    <file relUrl="scripts/esriApiExtensions.js" publishTime="09/26/2011 09:08:59" />
    <file relUrl="scripts/addressLocator.js" publishTime="08/15/2011 12:47:54" />
    <file relUrl="style/functionalClass.css" publishTime="11/07/2011 14:22:28" />
    <file relUrl="Metadata.ashx" publishTime="07/12/2011 14:23:51" />
    <file relUrl="scripts/modernizr.js" publishTime="10/12/2011 14:07:10" />
    <file relUrl="GetRoutes.ashx" publishTime="07/21/2011 14:17:26" />
    <file relUrl="scripts/layerList.js" publishTime="11/08/2011 14:06:56" />
    <file relUrl="scripts/index.js" publishTime="01/25/2012 11:08:41" />
    <file relUrl="images/loading-bar.gif" publishTime="07/14/2011 14:32:29" />
    <file relUrl="images/locationInfo/sprites.png" publishTime="07/12/2011 16:58:38" />
    <file relUrl="RouteListDemo.html" publishTime="11/07/2011 14:22:28" />
    <file relUrl="scripts/customLegend.js" publishTime="11/07/2011 14:22:28" />
    <file relUrl="scripts/lrsTools.js" publishTime="11/08/2011 10:50:58" />
    <file relUrl="images/navigation/sprites.png" publishTime="11/08/2011 16:40:31" />
    <file relUrl="MapIcon.ashx" publishTime="06/13/2011 14:51:05" />
    <file relUrl="bin/ICSharpCode.SharpZipLib.dll" publishTime="07/13/2011 14:14:49" />
    <file relUrl="style/addressLocator.css" publishTime="08/04/2011 10:22:28" />
    <file relUrl="MapIconGenerator.htm" publishTime="06/21/2011 09:39:51" />
    <file relUrl="help/milepost.html" publishTime="07/06/2011 14:50:10" />
    <file relUrl="style/fgdcPlus.css" publishTime="08/12/2011 09:52:36" />
    <file relUrl="images/camera.png" publishTime="04/08/2011 15:56:07" />
    <file relUrl="scripts/jquery.pnotify.js" publishTime="03/16/2011 09:42:00" />
    <file relUrl="images/layerList/treeMinus10.gif" publishTime="11/02/2011 14:58:23" />
    <file relUrl="scripts/config.js" publishTime="12/01/2011 08:29:58" />
    <file relUrl="scripts/jquery.cookie.js" publishTime="07/05/2011 16:57:31" />
    <file relUrl="lrsToolsTemplate.html" publishTime="08/04/2011 15:28:38" />
    <file relUrl="scripts/jquery.ba-bbq.min.js" publishTime="07/15/2011 13:27:08" />
    <file relUrl="scripts/config.internal-RFIP.js" publishTime="01/05/2012 14:39:22" />
    <file relUrl="help/location_info.html" publishTime="07/06/2011 14:50:10" />
    <file relUrl="scripts/fgdcPlus.js" publishTime="08/15/2011 12:47:54" />
    <file relUrl="IdentifyTemplate.html" publishTime="09/07/2011 14:44:39" />
    <file relUrl="proxy.config" publishTime="11/28/2011 17:31:31" />
    <file relUrl="images/legend/LegendSprites.png" publishTime="04/13/2011 11:57:08" />
    <file relUrl="scripts/config.internal-Freight.js" publishTime="01/05/2012 14:39:22" />
    <file relUrl="scripts/jquery.ba-bbq.js" publishTime="03/16/2011 09:42:00" />
    <file relUrl="help/navigation.html" publishTime="10/12/2011 14:07:10" />
    <file relUrl="images/layerList/sliderSprites.png" publishTime="11/02/2011 14:58:23" />
  </publishProfile>
  <publishProfile publishUrl="\\wsdot\resources\Topics\Software\Deployments\Prod\CGIS\GeoPortal" deleteExistingFiles="True" ftpAnonymousLogin="False" ftpPassiveMode="True" msdeploySite="" msdeploySiteID="" msdeployRemoteSitePhysicalPath="" msdeployAllowUntrustedCertificate="False" msdeploySkipExtraFilesOnServer="True" msdeployMarkAsApp="False" profileName="Production" publishMethod="FileSystem" replaceMatchingFiles="False" userName="" savePWD="False" userPWD="" SelectedForPublish="False">
    <file relUrl="bin/GeoPortal.pdb" publishTime="01/24/2012 15:41:52" />
    <file relUrl="images/ajax-loader.gif" publishTime="03/21/2011 13:56:45" />
    <file relUrl="scripts/htmlPopupExtensions.js" publishTime="12/21/2011 12:27:32" />
    <file relUrl="style/layerList.css" publishTime="11/08/2011 10:50:58" />
    <file relUrl="style/identify.css" publishTime="08/01/2011 13:29:55" />
    <file relUrl="help/zoom_controls.html" publishTime="10/12/2011 14:07:10" />
    <file relUrl="style/layerSorter.css" publishTime="11/08/2011 17:07:17" />
    <file relUrl="help/navigation.html" publishTime="10/12/2011 14:07:10" />
    <file relUrl="bin/GeoPortal.dll" publishTime="01/24/2012 15:41:52" />
    <file relUrl="proxy.ashx" publishTime="04/22/2011 12:22:41" />
    <file relUrl="scripts/addressLocator.js" publishTime="08/15/2011 12:47:54" />
    <file relUrl="web.config" publishTime="01/24/2012 15:42:02" />
    <file relUrl="scripts/toc.js" publishTime="11/07/2011 14:22:28" />
    <file relUrl="FunctionalClassLegend.html" publishTime="11/07/2011 14:22:28" />
    <file relUrl="images/WsdotBasemapThumbnail.jpg" publishTime="05/25/2011 12:49:05" />
    <file relUrl="style/index.css" publishTime="01/25/2012 12:50:43" />
    <file relUrl="images/NorthArrow.png" publishTime="03/22/2011 16:21:43" />
    <file relUrl="ReadMe.html" publishTime="11/07/2011 14:32:43" />
    <file relUrl="help/measure.html" publishTime="07/06/2011 13:42:43" />
    <file relUrl="index.html" publishTime="01/23/2012 16:24:50" />
    <file relUrl="images/greenlogo.png" publishTime="02/23/2011 08:50:45" />
    <file relUrl="images/layerList/contextMenu.png" publishTime="11/02/2011 14:58:23" />
    <file relUrl="scripts/jquery.pnotify.min.js" publishTime="07/15/2011 13:27:08" />
    <file relUrl="GraphicExport.ashx" publishTime="07/05/2011 16:57:31" />
    <file relUrl="images/navigation/FeedbackIcon.png" publishTime="07/01/2011 10:35:45" />
    <file relUrl="scripts/json2.js" publishTime="01/26/2011 10:03:51" />
    <file relUrl="style/jquery.pnotify.default.icons.css" publishTime="03/16/2011 09:47:53" />
    <file relUrl="style/jquery.pnotify.default.css" publishTime="03/16/2011 09:47:53" />
    <file relUrl="scripts/layerSorter.js" publishTime="11/08/2011 16:40:31" />
    <file relUrl="scripts/cameraGraphicsLayer.js" publishTime="08/15/2011 12:47:54" />
    <file relUrl="style/locationInfo.css" publishTime="07/12/2011 16:58:38" />
    <file relUrl="images/layerList/treePlus10.gif" publishTime="11/02/2011 14:58:23" />
    <file relUrl="scripts/extentSelect.js" publishTime="10/12/2011 14:07:10" />
    <file relUrl="scripts/esriApiExtensions.js" publishTime="09/26/2011 09:08:59" />
    <file relUrl="style/functionalClass.css" publishTime="11/07/2011 14:22:28" />
    <file relUrl="Metadata.ashx" publishTime="07/12/2011 14:23:51" />
    <file relUrl="scripts/modernizr.js" publishTime="10/12/2011 14:07:10" />
    <file relUrl="GetRoutes.ashx" publishTime="07/21/2011 14:17:26" />
    <file relUrl="scripts/layerList.js" publishTime="11/08/2011 14:06:56" />
    <file relUrl="scripts/index.js" publishTime="01/25/2012 11:08:41" />
    <file relUrl="images/loading-bar.gif" publishTime="07/14/2011 14:32:29" />
    <file relUrl="images/locationInfo/sprites.png" publishTime="07/12/2011 16:58:38" />
    <file relUrl="RouteListDemo.html" publishTime="11/07/2011 14:22:28" />
    <file relUrl="scripts/customLegend.js" publishTime="11/07/2011 14:22:28" />
    <file relUrl="scripts/lrsTools.js" publishTime="11/08/2011 10:50:58" />
    <file relUrl="images/navigation/sprites.png" publishTime="11/08/2011 16:40:31" />
    <file relUrl="bin/ICSharpCode.SharpZipLib.dll" publishTime="07/13/2011 14:14:49" />
    <file relUrl="images/layerList/sliderSprites.png" publishTime="11/02/2011 14:58:23" />
    <file relUrl="style/addressLocator.css" publishTime="08/04/2011 10:22:28" />
    <file relUrl="MapIconGenerator.htm" publishTime="06/21/2011 09:39:51" />
    <file relUrl="help/milepost.html" publishTime="07/06/2011 14:50:10" />
    <file relUrl="style/fgdcPlus.css" publishTime="08/12/2011 09:52:36" />
    <file relUrl="images/camera.png" publishTime="04/08/2011 15:56:07" />
    <file relUrl="scripts/jquery.pnotify.js" publishTime="03/16/2011 09:42:00" />
    <file relUrl="images/layerList/treeMinus10.gif" publishTime="11/02/2011 14:58:23" />
    <file relUrl="scripts/config.js" publishTime="12/01/2011 08:29:58" />
    <file relUrl="scripts/jquery.cookie.js" publishTime="07/05/2011 16:57:31" />
    <file relUrl="images/legend/LegendSprites.png" publishTime="04/13/2011 11:57:08" />
    <file relUrl="lrsToolsTemplate.html" publishTime="08/04/2011 15:28:38" />
    <file relUrl="scripts/jquery.ba-bbq.min.js" publishTime="07/15/2011 13:27:08" />
    <file relUrl="scripts/config.internal-RFIP.js" publishTime="01/05/2012 14:39:22" />
    <file relUrl="help/location_info.html" publishTime="07/06/2011 14:50:10" />
    <file relUrl="scripts/fgdcPlus.js" publishTime="08/15/2011 12:47:54" />
    <file relUrl="IdentifyTemplate.html" publishTime="09/07/2011 14:44:39" />
    <file relUrl="proxy.config" publishTime="11/28/2011 17:31:31" />
    <file relUrl="bin/Google.KML.dll" publishTime="07/13/2011 14:14:49" />
    <file relUrl="scripts/config.internal-Freight.js" publishTime="01/05/2012 14:39:22" />
    <file relUrl="scripts/jquery.ba-bbq.js" publishTime="03/16/2011 09:42:00" />
    <file relUrl="MapIcon.ashx" publishTime="06/13/2011 14:51:05" />
    <file relUrl="images/FCBasemapThumbnail.png" publishTime="05/25/2011 12:52:57" />
  </publishProfile>
</publishData>